{ "nodes":[ {"id": 0, "group" :0}, {"id": 1, "group" :3}, {"id": 11, "group" :5}, {"id": 16, "group" :2}, {"id": 23, "group" :4}, {"id": 39, "group" :6}, {"id": 46, "group" :1}, {"id": 54, "group" :7}], "links": [{"source": 0, "target": 1}, {"source": 0, "target": 11}, {"source": 0, "target": 23}, {"source": 0, "target": 16}, {"source": 11, "target": 23}, {"source": 11, "target": 16}, {"source": 11, "target": 54}, {"source": 11, "target": 46}, {"source": 11, "target": 39}, {"source": 16, "target": 23}, {"source": 23, "target": 39}, {"source": 39, "target": 54}, {"source": 46, "target": 54}]}